LICENSE
README.md
setup.py
PyEasyQiwi/__init__.py
PyEasyQiwi/errors.py
PyEasyQiwi.egg-info/PKG-INFO
PyEasyQiwi.egg-info/SOURCES.txt
PyEasyQiwi.egg-info/dependency_links.txt
PyEasyQiwi.egg-info/requires.txt
PyEasyQiwi.egg-info/top_level.txt
PyEasyQiwi/qiwi_service/__init__.py
PyEasyQiwi/qiwi_service/recourse.py
PyEasyQiwi/qiwi_service/support_module.py